data_metric_connector/__init__.py
data_metric_connector/connectors/__init__.py
data_metric_connector/connectors/mongo/__init__.py
data_metric_connector/connectors/mongo/connect.py
data_metric_connector/connectors/mongo/operations.py
data_metric_connector/connectors/mysql/__init__.py
data_metric_connector/connectors/mysql/connect.py
data_metric_connector/connectors/mysql/meta_sql/__init__.py
data_metric_connector/connectors/mysql/meta_sql/meta.sql
data_metric_connector/connectors/mysql/operations.py
data_metric_connector/logger/__init__.py
data_metric_connector/logger/logger.py
data_metric_connector/utils/__init__.py
data_metric_connector/utils/file_size.py
data_metrics_connectors-0.1.0.dist-info/LICENSE
data_metrics_connectors-0.1.0.dist-info/WHEEL
data_metrics_connectors-0.1.0.dist-info/METADATA
data_metrics_connectors-0.1.0.dist-info/RECORD
