Metadata-Version: 2.1
Name: data-metrics-connectors
Version: 0.1.0
Summary: 
License: MIT
Author: AADARSH GAIKWAD
Author-email: aadarshgaikwad96@gmail.com
Requires-Python: >=3.9,<4.0
Classifier: License :: OSI Approved :: MIT License
Classifier: Programming Language :: Python :: 3
Classifier: Programming Language :: Python :: 3.10
Classifier: Programming Language :: Python :: 3.9
Provides-Extra: lint
Requires-Dist: flake8-black (>=0.3.2,<0.4.0)
Requires-Dist: mongoengine (>=0.24.0,<0.25.0)
Requires-Dist: mysql-connector-python (>=8.0.28,<9.0.0)
